labctrl/__init__.py
labctrl/errors.py
labctrl/instrument.py
labctrl/logger.py
labctrl/resource.py
labctrl/server.py
labctrl/settings.py
labctrl/stage.py
labctrl/yamlizer.py
labctrl-0.4.3.dist-info/entry_points.txt
labctrl-0.4.3.dist-info/LICENSE.md
labctrl-0.4.3.dist-info/WHEEL
labctrl-0.4.3.dist-info/METADATA
labctrl-0.4.3.dist-info/RECORD
