Metadata-Version: 2.1
Name: labctrl
Version: 0.4.3
Summary: A unified framework for controlling and visualizing data collected from programmable lab instruments
Author: Atharv Joshi
Author-email: atharvjoshi@ymail.com
Requires-Python: >=3.9,<3.11
Classifier: Programming Language :: Python :: 3
Classifier: Programming Language :: Python :: 3.9
Classifier: Programming Language :: Python :: 3.10
Requires-Dist: PyYAML (>=6.0,<7.0)
Requires-Dist: Pyro5 (>=5.13.1,<6.0.0)
Requires-Dist: h5py (>=3.6.0,<4.0.0)
Requires-Dist: loguru (>=0.6.0,<0.7.0)
Requires-Dist: numpy (>=1.21.3,<2.0.0)
